arxify/__init__.py
arxify/arxify.py
arxify-1.3.2.dist-info/licenses/LICENSE
arxify-1.3.2.dist-info/METADATA
arxify-1.3.2.dist-info/WHEEL
arxify-1.3.2.dist-info/entry_points.txt
arxify-1.3.2.dist-info/top_level.txt
arxify-1.3.2.dist-info/RECORD
