Metadata-Version: 2.4
Name: arxify
Version: 1.3.2
Summary: Pack a latex project into an arXiv compatible archive.
Author-email: Tim Schneider <tim@robot-learning.de>
License: MIT
Project-URL: Homepage, https://github.com/TimSchneider42/arxify
Classifier: Intended Audience :: Science/Research
Classifier: License :: OSI Approved :: MIT License
Classifier: Operating System :: POSIX :: Linux
Classifier: Programming Language :: Python :: 3.10
Requires-Python: >=3.10
License-File: LICENSE
Requires-Dist: watchdog
Dynamic: license-file
